songsheet/__init__.py
songsheet-0.7a0.dist-info/LICENSE
songsheet-0.7a0.dist-info/METADATA
songsheet-0.7a0.dist-info/WHEEL
songsheet-0.7a0.dist-info/top_level.txt
songsheet-0.7a0.dist-info/RECORD
