Metadata-Version: 2.1
Name: songsheet
Version: 0.7a0
Summary: Parses songsheet strings
Home-page: https://github.com/kahunacohen/songsheet
Author: Aaron Cohen
Author-email: aaroncohendev@gmail.com
License: MIT
Download-URL: https://pypi.org/project/songsheet/
Keywords: music,lyrics
Platform: UNKNOWN
Classifier: Development Status :: 3 - Alpha
Classifier: Intended Audience :: Developers
Classifier: Topic :: Artistic Software
Classifier: License :: OSI Approved :: MIT License
Classifier: Programming Language :: Python :: 3.6
Classifier: Programming Language :: Python :: 3.7
